nestconfig/__init__.py
nestconfig/nest_config.py
nestconfig-0.2.0.dist-info/LICENSE
nestconfig-0.2.0.dist-info/METADATA
nestconfig-0.2.0.dist-info/WHEEL
nestconfig-0.2.0.dist-info/top_level.txt
nestconfig-0.2.0.dist-info/RECORD
