Metadata-Version: 2.1
Name: nestconfig
Version: 0.2.0
Summary: Type-safe configuration management with support for nested dataclasses
Home-page: https://github.com/zeyun-zhong/nestconfig
Author: Zeyun Zhong
Author-email: zeyun.zhong@kit.edu
Classifier: Programming Language :: Python :: 3
Classifier: License :: OSI Approved :: MIT License
Classifier: Operating System :: OS Independent
Requires-Python: >=3.7
License-File: LICENSE
Requires-Dist: PyYAML
